README.md
setup.cfg
setup.py
pybusent/__init__.py
pybusent/entities.py
pybusent/entities_advanced.py
pybusent/exceptions.py
pybusent/helpers.py
pybusent/sorting.py
pybuses_entities.egg-info/PKG-INFO
pybuses_entities.egg-info/SOURCES.txt
pybuses_entities.egg-info/dependency_links.txt
pybuses_entities.egg-info/requires.txt
pybuses_entities.egg-info/top_level.txt