Metadata-Version: 2.1
Name: pybuses-entities
Version: 0.0.1
Summary: Data classes to work with Stops and Buses/vehicles on a public transportation network
Home-page: https://github.com/David-Lor/PyBuses
Author: David Lorenzo
License: Apache 2.0
Platform: UNKNOWN
Classifier: Development Status :: 3 - Alpha
Classifier: Intended Audience :: Developers
Classifier: License :: OSI Approved :: MIT License
Classifier: Programming Language :: Python :: 3
Classifier: Programming Language :: Python :: 3.6
Classifier: Programming Language :: Python :: 3.7
